[
    {
        "title": "1994 FIFA World Cup",
        "tables": [
            [
                {
                    "Los Angeles": "Rose Bowl",
                    "San Francisco": "Stanford Stadium",
                    "Detroit": "Pontiac Silverdome",
                    "New York/New Jersey": "Giants Stadium"
                },
                {
                    "Los Angeles": "Capacity: 94,194",
                    "San Francisco": "Capacity: 84,147",
                    "Detroit": "Capacity: 77,557",
                    "New York/New Jersey": "Capacity: 76,322"
                },
                {
                    "Los Angeles": "200px",
                    "San Francisco": "200px",
                    "Detroit": "200px",
                    "New York/New Jersey": "200px"
                },
                {
                    "Los Angeles": "Dallas",
                    "San Francisco": "USA"
                },
                {
                    "Los Angeles": "Cotton Bowl",
                    "San Francisco": "USA"
                },
                {
                    "Los Angeles": "Capacity: 64,000",
                    "San Francisco": "USA"
                },
                {
                    "Los Angeles": "200px",
                    "San Francisco": "USA"
                },
                {
                    "Los Angeles": "Chicago",
                    "San Francisco": "Orlando",
                    "Detroit": "Boston ([[Foxborough, Massachusetts]])",
                    "New York/New Jersey": "Washington, D.C."
                },
                {
                    "Los Angeles": "Soldier Field",
                    "San Francisco": "Citrus Bowl",
                    "Detroit": "Foxboro Stadium",
                    "New York/New Jersey": "Robert F. Kennedy Memorial Stadium"
                },
                {
                    "Los Angeles": "Capacity: 63,160",
                    "San Francisco": "Capacity: 62,387",
                    "Detroit": "Capacity: 54,456",
                    "New York/New Jersey": "Capacity: 53,121"
                },
                {
                    "Los Angeles": "200px",
                    "San Francisco": "200px",
                    "Detroit": "200px",
                    "New York/New Jersey": "200px"
                }
            ],
            [
                {
                    "Pot 1Top-seeded teams (top 5 teams + hosts)": "USA (hosts) (23, OR=18) GER (1990 champions) (1, OR=1) ARG (8, OR=2) ITA (4, OR=3) BRA (3, OR=4) BEL (27, OR=5)",
                    "Pot 2Africa & Americas(CAF, CONCACAF and CONMEBOL)": "MEX (16, OR=8) CMR (24, OR=9) MAR (28, OR=11) COL (17, OR=13) NGA (11, OR=new) BOL civil (43, OR=new)",
                    "Pot 3Best unseeded from Europe  (UEFA)": "ESP (5, OR=6) RUS (19, OR=7) IRL (14, OR=10) ROU (7, OR=12) NED (2, OR=14) BUL (29, OR=15)",
                    "Pot 4Asia and worst ranked from Europe (AFC and UEFA)": "KOR 1984 (37, OR=16) SWE (10, OR=17) GRE (31, OR=new) NOR (6, OR=new) SUI (12, OR=new) KSA (34, OR=new)"
                }
            ],
            [
                {
                    "Group A(blue)": "USA (23, OR=18) SUI (12, OR=new) COL (17, OR=13) ROU (7, OR=12)",
                    "Group B(orange)": "BRA (3, OR=4) RUS (19, OR=7) CMR (24, OR=9) SWE (10, OR=17)",
                    "Group C(green)": "GER (1, OR=1) BOL civil (43, OR=new) ESP (5, OR=6) KOR 1984 (37, OR=16)",
                    "Group D(white)": "ARG (8, OR=2) GRE (31, OR=new) NGA (11, OR=new) BUL (29, OR=15)",
                    "Group E(pink)": "ITA (4, OR=3) IRL (14, OR=10) NOR (6, OR=new) MEX (16, OR=8)",
                    "Group F(black)": "BEL (27, OR=5) MAR (28, OR=11) NED (2, OR=14) KSA (34, OR=new)"
                }
            ],
            [
                {
                    "Golden Shoe": "BUL Hristo Stoichkov RUS Oleg Salenko",
                    "Golden Ball": "BRA Rom\u00e1rio",
                    "Yashin Award": "BEL Michel Preud'homme",
                    "Best Young Player": "NED Marc Overmars",
                    "FIFA Fair Play Trophy": "BRA",
                    "Most Entertaining Team": "BRA"
                }
            ],
            [
                {
                    "Goalkeeper": "BEL Michel Preud'homme",
                    "Defenders": "BRA Jorginho BRA M\u00e1rcio Santos ITA Paolo Maldini",
                    "Midfielders": "BRA Dunga BUL Krasimir Balakov ROU Gheorghe Hagi SWE Tomas Brolin",
                    "Forwards": "BRA Rom\u00e1rio BUL Hristo Stoichkov ITA Roberto Baggio"
                }
            ],
            [
                {
                    "": "17",
                    "Team": "BRA"
                },
                {
                    "": "14",
                    "Team": "ITA"
                },
                {
                    "": "12",
                    "Team": "SWE"
                },
                {
                    "": "10",
                    "Team": "BUL"
                },
                {
                    "": "Eliminated in the quarter-finals"
                },
                {
                    "": "10",
                    "Team": "GER"
                },
                {
                    "": "10",
                    "Team": "ROU"
                },
                {
                    "": "9",
                    "Team": "NED"
                },
                {
                    "": "8",
                    "Team": "ESP"
                },
                {
                    "": "Eliminated in the round of 16"
                },
                {
                    "": "6",
                    "Team": "NGA"
                },
                {
                    "": "6",
                    "Team": "ARG"
                },
                {
                    "": "6",
                    "Team": "BEL"
                },
                {
                    "": "6",
                    "Team": "KSA"
                },
                {
                    "": "5",
                    "Team": "MEX"
                },
                {
                    "": "4",
                    "Team": "USA"
                },
                {
                    "": "4",
                    "Team": "SUI"
                },
                {
                    "": "4",
                    "Team": "IRL"
                },
                {
                    "": "Eliminated in the group stage"
                },
                {
                    "": "4",
                    "Team": "NOR"
                },
                {
                    "": "3",
                    "Team": "RUS"
                },
                {
                    "": "3",
                    "Team": "COL"
                },
                {
                    "": "2",
                    "Team": "KOR 1984"
                },
                {
                    "": "1",
                    "Team": "BOL civil"
                },
                {
                    "": "1",
                    "Team": "CMR"
                },
                {
                    "": "0",
                    "Team": "MAR"
                },
                {
                    "": "0",
                    "Team": "GRE"
                }
            ]
        ]
    },
    {
        "title": "Nippon Professional Baseball",
        "tables": [
            [
                {
                    "Team": "Central League"
                },
                {
                    "Team": "Chunichi Dragons",
                    "City": "Nagoya , Aichi",
                    "Stadium": "Vantelin Dome Nagoya",
                    "Capacity": "40500",
                    "Coordinates": "35 11 15.36 N 136 56 57.119 E type:landmark_region:JP",
                    "Founded": "January 15, 1936",
                    "Manager": "Kazuyoshi Tatsunami"
                },
                {
                    "Team": "Hanshin Tigers",
                    "City": "HQ in Nishinomiya , Hy\u014dgo Plays between Osaka and Hyogo",
                    "Stadium": "Hanshin Koshien Stadium Kyocera Dome Osaka",
                    "Capacity": "47,757\nand 36,477",
                    "Coordinates": "34 43 16.34 N 135 21 41.84 E type:landmark_region:JP 34 40 9.48 N 135 28 33.97 E type:landmark_region:JP",
                    "Founded": "December 10, 1935",
                    "Manager": "Akinobu Okada"
                },
                {
                    "Team": "Hiroshima Toyo Carp",
                    "City": "Hiroshima , Hiroshima",
                    "Stadium": "Mazda Stadium",
                    "Capacity": "32000",
                    "Coordinates": "34 23 33 N 132 29 2.4 E type:landmark_region:JP",
                    "Founded": "December 5, 1949",
                    "Manager": "Takahiro Arai"
                },
                {
                    "Team": "Tokyo Yakult Swallows",
                    "City": "Shinjuku , Tokyo",
                    "Stadium": "Meiji Jingu Stadium",
                    "Capacity": "37933",
                    "Coordinates": "35 40 28.3 N 139 43 1.4 E type:landmark_region:JP",
                    "Founded": "January 12, 1950",
                    "Manager": "Shingo Takatsu"
                },
                {
                    "Team": "Yokohama DeNA BayStars",
                    "City": "Yokohama , Kanagawa",
                    "Stadium": "Yokohama Stadium",
                    "Capacity": "30000",
                    "Coordinates": "35 26 36.34 N 139 38 24.36 E type:landmark_region:JP",
                    "Founded": "December 15, 1949",
                    "Manager": "Daisuke Miura"
                },
                {
                    "Team": "Yomiuri Giants",
                    "City": "Bunky\u014d , Tokyo",
                    "Stadium": "Tokyo Dome",
                    "Capacity": "46000",
                    "Coordinates": "35 42 20 N 139 45 7 E type:landmark_region:JP",
                    "Founded": "December 26, 1934",
                    "Manager": "Shinnosuke Abe"
                },
                {
                    "Team": "Pacific League"
                },
                {
                    "Team": "Chiba Lotte Marines",
                    "City": "Chiba , Chiba",
                    "Stadium": "ZOZO Marine Stadium",
                    "Capacity": "30000",
                    "Coordinates": "35 38 42.86 N 140 1 51.32 E type:landmark_region:JP",
                    "Founded": "November 26, 1949",
                    "Manager": "Masato Yoshii"
                },
                {
                    "Team": "Fukuoka SoftBank Hawks",
                    "City": "Fukuoka , Fukuoka",
                    "Stadium": "Mizuho PayPay Dome Fukuoka",
                    "Capacity": "40000",
                    "Coordinates": "33 35 43 N 130 21 44 E type:landmark_region:JP",
                    "Founded": "February 22, 1938",
                    "Manager": "Hiroki Kokubo"
                },
                {
                    "Team": "Hokkaido Nippon-Ham Fighters",
                    "City": "Kitahiroshima , Hokkaid\u014d",
                    "Stadium": "ES CON Field Hokkaido",
                    "Capacity": "35000",
                    "Coordinates": "42 59 23 N 141 32 58 E type:landmark_region:JP",
                    "Founded": "November 6, 1945",
                    "Manager": "Tsuyoshi Shinjo"
                },
                {
                    "Team": "Orix Buffaloes",
                    "City": "HQ in Osaka Plays between Osaka and Hyogo",
                    "Stadium": "Kyocera Dome Osaka Hotto Motto Field",
                    "Capacity": "36,477\nand\n35,000",
                    "Coordinates": "34 40 9.48 N 135 28 33.97 E type:landmark_region:JP 34 40 50.37 N 135 4 24.3 E type:landmark_region:JP",
                    "Founded": "January 23, 1936",
                    "Manager": "Satoshi Nakajima"
                },
                {
                    "Team": "Saitama Seibu Lions",
                    "City": "Tokorozawa , Saitama",
                    "Stadium": "Belluna Dome",
                    "Capacity": "33921",
                    "Coordinates": "35 46 6.6 N 139 25 13.8 E type:landmark_region:JP",
                    "Founded": "November 26, 1949",
                    "Manager": "Kazuo Matsui"
                },
                {
                    "Team": "Tohoku Rakuten Golden Eagles",
                    "City": "Sendai , Miyagi",
                    "Stadium": "Rakuten Mobile Park Miyagi",
                    "Capacity": "30508",
                    "Coordinates": "38 15 22.34 N 140 54 9 E type:landmark_region:JP",
                    "Founded": "November 2, 2004",
                    "Manager": "Toshiaki Imae"
                }
            ],
            [
                {
                    "Team": "Defunct Clubs"
                },
                {
                    "Team": "Nishi Nippon Pirates",
                    "City": "Fukuoka , Fukuoka",
                    "Stadium": "52 stadiums in 29 prefectures across Japan [https://npb.jp/news/detail/20210324_02.html \u3010\u8a18\u9332\u54e1\u30b3\u30e9\u30e0\u301129\u90fd\u9053\u5e9c\u770c\u300152\u7403\u5834\u3092\u99c6\u3051\u5de1\u3063\u305f\u897f\u65e5\u672c\u30d1\u30a4\u30ec\u30fc\u30c4] \uff08\u65e5\u672c\u91ce\u7403\u6a5f\u69cb\uff09",
                    "Founded": "1950",
                    "Ceased Operations": "January 30, 1951",
                    "Notes": "Merged with the Nishitetsu Clippers to form the Fukuoka Nishitetsu Lions (now known as the Saitama Seibu Lions )"
                },
                {
                    "Team": "Shochiku Robins",
                    "City": "Kyoto , Kyoto",
                    "Stadium": "Kinugasa Stadium",
                    "Founded": "1936",
                    "Ceased Operations": "January 1, 1953",
                    "Notes": "Merged with the Taiyo Whales to form the Taiyo-Shochiku Robins (now known as the Yokohama DeNA BayStars )"
                },
                {
                    "Team": "Takahashi Unions",
                    "City": "Kawasaki , Kanagawa",
                    "Stadium": "Kawasaki Stadium",
                    "Founded": "1954",
                    "Ceased Operations": "February 25, 1957 Yomiuri Shimbun, February 26, 1957, page 4, \"Daiei and Takahashi to merge in Pacific League this year, 7 team system, Owners' Meeting Fails to Realize Six Team System\"",
                    "Notes": "Merged with the Daiei Stars to form the Daiei Unions"
                },
                {
                    "Team": "Daiei Unions",
                    "City": "Bunky\u014d , Tokyo",
                    "Stadium": "Korakuen Stadium",
                    "Founded": "1946",
                    "Ceased Operations": "November 24, 1957 Mainichi Shimbun, November 25, 1957, page 7 [Pacific's 6-team system realized; Mainichi and Daiei to merge in the middle of next month]",
                    "Notes": "Merged with the Mainichi Orions to form the Daimai Orions (now known as the Chiba Lotte Marines )"
                },
                {
                    "Team": "Osaka Kintetsu Buffaloes",
                    "City": "Osaka , Osaka",
                    "Stadium": "Kyocera Dome Osaka",
                    "Founded": "1949",
                    "Ceased Operations": "December 1, 2004",
                    "Notes": "Merged with the Orix BlueWave to form the Orix Buffaloes"
                }
            ],
            [
                {
                    "Locality": "Greater Sapporo",
                    "1950": "&nbsp;",
                    "1951\u20131952": "Hokkaido Nippon-Ham Fighters (PL), 2004\u2013present Based in [[Kitahiroshima, Hokkaido|Kitahiroshima]] since 2023"
                },
                {
                    "Locality": "Sendai",
                    "1950": "&nbsp;",
                    "1951\u20131952": "Lotte Orions (PL), 1973\u20131977",
                    "1953": "&nbsp;",
                    "1954": "Tohoku Rakuten Golden Eagles (PL), 2005\u2013present"
                },
                {
                    "Locality": "Greater Tokyo",
                    "1950": "Kokutetsu Swallows / Sankei Atoms / Yakult Swallows (CL), 1950\u2013present"
                },
                {
                    "Locality": "Greater Tokyo",
                    "1950": "Yomiuri Giants (CL), 1950\u2013present"
                },
                {
                    "Locality": "Greater Tokyo",
                    "1950": "Toei Flyers / Nippon-Ham Fighters (PL), 1950\u20132003"
                },
                {
                    "Locality": "Greater Tokyo",
                    "1950": "Mainichi/Daimai/Tokyo/Lotte Orions (PL), 1950\u20131972",
                    "1951\u20131952": "&nbsp;",
                    "1953": "Lotte Orions / Chiba Lotte Marines (PL), 1978\u2013present"
                },
                {
                    "Locality": "Greater Tokyo",
                    "1950": "&nbsp;",
                    "1951\u20131952": "Takahashi Unions (PL), 1954\u20131956",
                    "1953": "Daiei Unions (PL), 1957",
                    "1954": "&nbsp;",
                    "1955\u20131956": "Saitama Seibu Lions (PL), 1979\u2013present"
                },
                {
                    "Locality": "Greater Tokyo",
                    "1950": "Daiei Stars (PL), 1950\u20131956",
                    "1953": "Daiei Unions (PL), 1957",
                    "1954": "&nbsp;",
                    "1955\u20131956": "Saitama Seibu Lions (PL), 1979\u2013present"
                },
                {
                    "Locality": "Greater Tokyo",
                    "1950": "&nbsp;",
                    "1951\u20131952": "Taiyo Whales / Yokohama BayStars (CL), 1955\u2013present"
                },
                {
                    "Locality": "Nagoya",
                    "1950": "Chunichi Dragons (CL), 1950\u2013present"
                },
                {
                    "Locality": "Greater Osaka",
                    "1950": "Hanshin Tigers (CL), 1950\u2013present"
                },
                {
                    "Locality": "Greater Osaka",
                    "1950": "Hankyu Braves / Orix BlueWave (PL), 1950\u20132004",
                    "1951\u20131952": "Orix Buffaloes (PL), 2005\u2013present"
                },
                {
                    "Locality": "Greater Osaka",
                    "1950": "Osaka Kintetsu Buffaloes (PL), 1950\u20132004",
                    "1951\u20131952": "Orix Buffaloes (PL), 2005\u2013present"
                },
                {
                    "Locality": "Greater Osaka",
                    "1950": "Nankai Hawks (PL), 1950\u20131988"
                },
                {
                    "Locality": "Greater Osaka",
                    "1950": "Shochiku Robins (CL), 1950\u20131954"
                },
                {
                    "Locality": "Hiroshima",
                    "1950": "Hiroshima Toyo Carp (CL), 1950\u2013present"
                },
                {
                    "Locality": "Shimonoseki",
                    "1950": "Taiyo Whales (CL), 1950\u20131952"
                },
                {
                    "Locality": "Fukuoka",
                    "1950": "Nishitetsu Lions (PL), 1950\u20131978",
                    "1951\u20131952": "&nbsp;",
                    "1953": "Fukuoka Daiei/SoftBank Hawks (PL), 1989\u2013present"
                },
                {
                    "Locality": "Fukuoka",
                    "1950": "Nishi Nippon Pirates (CL), 1950"
                }
            ],
            [
                {
                    "Team": "Yomiuri Giants",
                    "Champions": "22",
                    "Runners-up": "14",
                    "Winning seasons": "1951 , 1952 , 1953 , 1955 , 1961 , 1963 , 1965 , 1966 , 1967 , 1968 , 1969 , 1970 , 1971 , 1972 , 1973 , 1981 , 1989 , 1994 , 2000 , 2002 , 2009 , 2012",
                    "Runners-up seasons": "1956 , 1957 , 1958 , 1959 , 1976 , 1977 , 1983 , 1987 , 1990 , 1996 , 2008 , 2013 , 2019 , 2020"
                },
                {
                    "Team": "Saitama Seibu Lions",
                    "Champions": "13",
                    "Runners-up": "8",
                    "Winning seasons": "1956 , 1957 , 1958 , 1982 , 1983 , 1986 , 1987 , 1988 , 1990 , 1991 , 1992 , 2004 , 2008",
                    "Runners-up seasons": "1954 , 1963 , 1985 , 1993 , 1994 , 1997 , 1998 , 2002"
                },
                {
                    "Team": "Fukuoka SoftBank Hawks",
                    "Champions": "11",
                    "Runners-up": "9",
                    "Winning seasons": "1959 , 1964 , 1999 , 2003 , 2011 , 2014 , 2015 , 2017 , 2018 , 2019 , 2020",
                    "Runners-up seasons": "1951 , 1952 , 1953 , 1955 , 1961 , 1965 , 1966 , 1973 , 2000"
                },
                {
                    "Team": "Tokyo Yakult Swallows",
                    "Champions": "6",
                    "Runners-up": "3",
                    "Winning seasons": "1978 , 1993 , 1995 , 1997 , 2001 , 2021",
                    "Runners-up seasons": "1992 , 2015 , 2022"
                },
                {
                    "Team": "Orix Buffaloes",
                    "Champions": "5",
                    "Runners-up": "10",
                    "Winning seasons": "1975 , 1976 , 1977 , 1996 , 2022",
                    "Runners-up seasons": "1967 , 1968 , 1969 , 1971 , 1972 , 1978 , 1984 , 1995 , 2021 , 2023"
                },
                {
                    "Team": "Chiba Lotte Marines",
                    "Champions": "4",
                    "Runners-up": "2",
                    "Winning seasons": "1950 , 1974 , 2005 , 2010",
                    "Runners-up seasons": "1960 , 1970"
                },
                {
                    "Team": "Hiroshima Toyo Carp",
                    "Champions": "3",
                    "Runners-up": "4",
                    "Winning seasons": "1979 , 1980 , 1984",
                    "Runners-up seasons": "1975 , 1986 , 1991 , 2016 , 2018"
                },
                {
                    "Team": "Hokkaido Nippon-Ham Fighters",
                    "Champions": "3",
                    "Runners-up": "4",
                    "Winning seasons": "1962 , 2006 , 2016",
                    "Runners-up seasons": "1981 , 2007 , 2009 , 2012"
                },
                {
                    "Team": "Chunichi Dragons",
                    "Champions": "2",
                    "Runners-up": "8",
                    "Winning seasons": "1954 , 2007",
                    "Runners-up seasons": "1974 , 1982 , 1988 , 1999 , 2004 , 2006 , 2010 , 2011"
                },
                {
                    "Team": "Yokohama DeNA BayStars",
                    "Champions": "2",
                    "Runners-up": "1",
                    "Winning seasons": "1960 , 1998",
                    "Runners-up seasons": "2017"
                },
                {
                    "Team": "Hanshin Tigers",
                    "Champions": "2",
                    "Runners-up": "5",
                    "Winning seasons": "1985 , 2023",
                    "Runners-up seasons": "1962 , 1964 , 2003 , 2005 , 2014"
                },
                {
                    "Team": "Tohoku Rakuten Golden Eagles",
                    "Champions": "1",
                    "Runners-up": "0",
                    "Winning seasons": "2013",
                    "Runners-up seasons": "\u2014"
                },
                {
                    "Team": "Osaka Kintetsu Buffaloes",
                    "Champions": "0",
                    "Runners-up": "4",
                    "Winning seasons": "\u2014",
                    "Runners-up seasons": "1979 , 1980 , 1989 , 2001"
                },
                {
                    "Team": "Shochiku Robins",
                    "Champions": "0",
                    "Runners-up": "1",
                    "Winning seasons": "\u2014",
                    "Runners-up seasons": "1950"
                }
            ],
            [
                {
                    "Player": "Central League",
                    "": "Pacific League",
                    "Year": "Overall"
                },
                {
                    "Player": "Batting Average"
                },
                {
                    "Player": "USA Randy Bass",
                    "": "0.389",
                    "Year": "1986"
                },
                {
                    "Player": "JPN Ichiro Suzuki",
                    "": "0.387",
                    "Year": "2000"
                },
                {
                    "Player": "JPN Ichiro Suzuki",
                    "": "0.385",
                    "Year": "1994"
                },
                {
                    "Player": "Home Runs <!-- https://npb.jp/bis/history/ssb_hr.html -->"
                },
                {
                    "Player": "NED Wladimir Balentien",
                    "": "60",
                    "Year": "2013"
                },
                {
                    "Player": "JPN Munetaka Murakami",
                    "": "56",
                    "Year": "2022"
                },
                {
                    "Player": "TWN Sadaharu Oh",
                    "": "55",
                    "Year": "1964"
                },
                {
                    "Player": "USA Tuffy Rhodes",
                    "": "55",
                    "Year": "2001"
                },
                {
                    "Player": "VEN Alex Cabrera",
                    "": "55",
                    "Year": "2002"
                },
                {
                    "Player": "RBIs"
                },
                {
                    "Player": "JPN Makoto Kozuru",
                    "": "161",
                    "Year": "1950"
                },
                {
                    "Player": "USA Bobby Rose",
                    "": "153",
                    "Year": "1999"
                },
                {
                    "Player": "JPN Makoto Imaoka",
                    "": "147",
                    "Year": "2005"
                },
                {
                    "Player": "Hits"
                },
                {
                    "Player": "JPN Shogo Akiyama",
                    "": "216",
                    "Year": "2015"
                },
                {
                    "Player": "USA Matt Murton",
                    "": "214",
                    "Year": "2010"
                },
                {
                    "Player": "JPN Ichiro Suzuki",
                    "": "210",
                    "Year": "1994"
                },
                {
                    "Player": "Stolen Bases <!-- https://npb.jp/bis/history/ssb_sb.html -->"
                },
                {
                    "Player": "JPN Yutaka Fukumoto",
                    "": "106",
                    "Year": "1972"
                },
                {
                    "Player": "JPN Yutaka Fukumoto",
                    "": "95",
                    "Year": "1973"
                },
                {
                    "Player": "JPN Yutaka Fukumoto",
                    "": "94",
                    "Year": "1974"
                },
                {
                    "Player": "Strikeouts <!-- https://npb.jp/bis/history/ssb_so.html -->"
                },
                {
                    "Player": "USA Ralph Bryant",
                    "": "204",
                    "Year": "1993"
                },
                {
                    "Player": "USA Ralph Bryant",
                    "": "198",
                    "Year": "1990"
                },
                {
                    "Player": "USA Ralph Bryant",
                    "": "187",
                    "Year": "1989"
                }
            ],
            [
                {
                    "Player": "Central League",
                    "": "Pacific League",
                    "Year": "Overall"
                },
                {
                    "Player": "ERA <!-- https://npb.jp/bis/history/ssp_era.html -->"
                },
                {
                    "Player": "JPN Minoru Murayama d",
                    "": "0.98",
                    "Year": "1970"
                },
                {
                    "Player": "JPN Kazuhisa Inao",
                    "": "1.06",
                    "Year": "1956"
                },
                {
                    "Player": "JPN Minoru Murayama",
                    "": "1.19",
                    "Year": "1959"
                },
                {
                    "Player": "Wins <!-- https://npb.jp/bis/history/ssp_w.html -->"
                },
                {
                    "Player": "JPN Kazuhisa Inao e",
                    "": "42",
                    "Year": "1961"
                },
                {
                    "Player": "JPN Juzo Sanada",
                    "": "39",
                    "Year": "1950"
                },
                {
                    "Player": "JPN Tadashi Sugiura",
                    "": "38",
                    "Year": "1959"
                },
                {
                    "Player": "Saves <!-- https://npb.jp/bis/history/ssp_sv.html -->"
                },
                {
                    "Player": "USA Dennis Sarfate",
                    "": "54",
                    "Year": "2017"
                },
                {
                    "Player": "JPN Hitoki Iwase",
                    "": "46",
                    "Year": "2005"
                },
                {
                    "Player": "JPN Kyuji Fujikawa",
                    "": "46",
                    "Year": "2007"
                },
                {
                    "Player": "Strikeouts <!-- https://npb.jp/bis/history/ssp_so.html -->"
                },
                {
                    "Player": "JPN Yutaka Enatsu",
                    "": "401",
                    "Year": "1968"
                },
                {
                    "Player": "JPN Kazuhisa Inao",
                    "": "353",
                    "Year": "1961"
                },
                {
                    "Player": "KOR Masaichi Kaneda",
                    "": "350",
                    "Year": "1955"
                }
            ],
            [
                {
                    "Player": "Batting average Ichiro Suzuki hit .353 for his Japanese career (1993\u20132000), but did not have enough at-bats to qualify for career leadership."
                },
                {
                    "Player": "USA Leron Lee",
                    "": "0.32",
                    "Years played": "1977\u20131987"
                },
                {
                    "Player": "JPN Tsutomu Wakamatsu",
                    "": "0.31918",
                    "Years played": "1971\u20131989"
                },
                {
                    "Player": "KOR Isao Harimoto",
                    "": "0.31915",
                    "Years played": "1959\u20131981"
                },
                {
                    "Player": "USA Greg Wells",
                    "": "0.317",
                    "Years played": "1983-1992"
                },
                {
                    "Player": "Home Runs List of top Nippon Professional Baseball home run hitters"
                },
                {
                    "Player": "TWN Sadaharu Oh",
                    "": "868",
                    "Years played": "1959\u20131980"
                },
                {
                    "Player": "JPN Katsuya Nomura",
                    "": "657",
                    "Years played": "1954\u20131980"
                },
                {
                    "Player": "JPN Hiromitsu Kadota",
                    "": "567",
                    "Years played": "1970\u20131992"
                },
                {
                    "Player": "Hits List of Nippon Professional Baseball career hits leaders"
                },
                {
                    "Player": "KOR Isao Harimoto",
                    "": "3085",
                    "Years played": "1959\u20131981"
                },
                {
                    "Player": "JPN Katsuya Nomura",
                    "": "2901",
                    "Years played": "1954\u20131980"
                },
                {
                    "Player": "TWN Sadaharu Oh",
                    "": "2786",
                    "Years played": "1959\u20131980"
                },
                {
                    "Player": "RBIs List of Nippon Professional Baseball players with 1,000 runs batted in"
                },
                {
                    "Player": "TWN Sadaharu Oh",
                    "": "2170",
                    "Years played": "1959\u20131980"
                },
                {
                    "Player": "JPN Katsuya Nomura",
                    "": "1988",
                    "Years played": "1954\u20131980"
                },
                {
                    "Player": "JPN Hiromitsu Kadota",
                    "": "1678",
                    "Years played": "1970\u20131992"
                },
                {
                    "Player": "Stolen Bases"
                },
                {
                    "Player": "JPN Yutaka Fukumoto",
                    "": "1065",
                    "Years played": "1969\u20131988"
                },
                {
                    "Player": "JPN Yoshinori Hirose",
                    "": "596",
                    "Years played": "1955\u20131977"
                },
                {
                    "Player": "JPN Isao Shibata",
                    "": "579",
                    "Years played": "1962\u20131981"
                },
                {
                    "Player": "Strikeouts"
                },
                {
                    "Player": "JPN Kazuhiro Kiyohara",
                    "": "1955",
                    "Years played": "1986\u20132008"
                },
                {
                    "Player": "JPN Motonobu Tanishige",
                    "": "1838",
                    "Years played": "1989\u20132015"
                },
                {
                    "Player": "JPN Koji Akiyama",
                    "": "1712",
                    "Years played": "1981\u20132002"
                },
                {
                    "Player": "OPS"
                },
                {
                    "Player": "TWN Sadaharu Oh",
                    "": "1.08",
                    "Years played": "1959\u20131980"
                },
                {
                    "Player": "JPN Hideki Matsui",
                    "": "0.995",
                    "Years played": "1993\u20132002"
                },
                {
                    "Player": "VEN Alex Cabrera",
                    "": "0.99",
                    "Years played": "2001\u20132012"
                }
            ],
            [
                {
                    "Player": "ERA"
                },
                {
                    "Player": "JPN Hideo Fujimoto",
                    "": "1.9",
                    "Years played": "1942\u20131955"
                },
                {
                    "Player": "Wins"
                },
                {
                    "Player": "JPN Masaichi Kaneda",
                    "": "400",
                    "Years played": "1950\u20131969"
                },
                {
                    "Player": "JPN Tetsuya Yoneda",
                    "": "350",
                    "Years played": "1956\u20131977"
                },
                {
                    "Player": "JPN Masaaki Koyama",
                    "": "320",
                    "Years played": "1953\u20131973"
                },
                {
                    "Player": "JPN Keishi Suzuki",
                    "": "317",
                    "Years played": "1966\u20131985"
                },
                {
                    "Player": "JPN Takehiko Bessho",
                    "": "310",
                    "Years played": "1942\u20131960"
                },
                {
                    "Player": "URS Victor Starffin",
                    "": "303",
                    "Years played": "1936\u20131955"
                },
                {
                    "Player": "Strikeouts List of top Nippon Professional Baseball strikeout pitchers"
                },
                {
                    "Player": "JPN Masaichi Kaneda",
                    "": "4490",
                    "Years played": "1950\u20131969"
                },
                {
                    "Player": "JPN Tetsuya Yoneda",
                    "": "3388",
                    "Years played": "1956\u20131977"
                },
                {
                    "Player": "JPN Masaaki Koyama",
                    "": "3159",
                    "Years played": "1953\u20131973"
                },
                {
                    "Player": "JPN Keishi Suzuki",
                    "": "3061",
                    "Years played": "1966\u20131985"
                },
                {
                    "Player": "Saves"
                },
                {
                    "Player": "JPN Hitoki Iwase",
                    "": "407",
                    "Years played": "1999\u20132018"
                },
                {
                    "Player": "JPN Shingo Takatsu",
                    "": "286",
                    "Years played": "1991\u20132003, 2006\u20132007"
                },
                {
                    "Player": "JPN Kazuhiro Sasaki",
                    "": "252",
                    "Years played": "1990\u20131999, 2004\u20132005"
                }
            ],
            [
                {
                    "Date": "June 28, 1950",
                    "Pitcher (Club)": "Hideo Fujimoto ( Yomiuri Giants )",
                    "Score": "4\u20130",
                    "Opponent": "Nishi-Nippon Pirates",
                    "Ballpark": "Aomori Stadium"
                },
                {
                    "Date": "June 19, 1955",
                    "Pitcher (Club)": "Fumio Takechi ( Kintetsu Pearls )",
                    "Score": "1\u20130",
                    "Opponent": "Daiei Stars",
                    "Ballpark": "\u014csaka Stadium"
                },
                {
                    "Date": "September 19, 1956",
                    "Pitcher (Club)": "Yoshitomo Miyaji ( Kokutetsu Swallows )",
                    "Score": "6\u20130",
                    "Opponent": "Hiroshima Carp",
                    "Ballpark": "Kanazawa Stadium"
                },
                {
                    "Date": "August 21, 1957",
                    "Pitcher (Club)": "Masaichi Kaneda ( Kokutetsu Swallows )",
                    "Score": "1\u20130",
                    "Opponent": "Chunichi Dragons",
                    "Ballpark": "Chunichi Stadium"
                },
                {
                    "Date": "July 19, 1958",
                    "Pitcher (Club)": "Sadao Nishimura ( Nishitetsu Lions )",
                    "Score": "1\u20130",
                    "Opponent": "Toei Flyers",
                    "Ballpark": "Komazawa Stadium"
                },
                {
                    "Date": "August 11, 1960",
                    "Pitcher (Club)": "Gentaro Shimada ( Taiy\u014d Whales )",
                    "Score": "1\u20130",
                    "Opponent": "\u014csaka Tigers",
                    "Ballpark": "Kawasaki Stadium"
                },
                {
                    "Date": "June 20, 1961",
                    "Pitcher (Club)": "Yoshimi Moritaki ( Kokutetsu Swallows )",
                    "Score": "1\u20130",
                    "Opponent": "Chunichi Dragons",
                    "Ballpark": "Korakuen Stadium"
                },
                {
                    "Date": "May 1, 1966",
                    "Pitcher (Club)": "Yoshiro Sasaki ( Taiy\u014d Whales )",
                    "Score": "1\u20130",
                    "Opponent": "Hiroshima Carp",
                    "Ballpark": "Hiroshima Municipal Stadium"
                },
                {
                    "Date": "May 12, 1966",
                    "Pitcher (Club)": "Tsutomu Tanaka ( Nishitetsu Lions )",
                    "Score": "2\u20130",
                    "Opponent": "Nankai Hawks",
                    "Ballpark": "Heiwadai Stadium"
                },
                {
                    "Date": "September 14, 1968",
                    "Pitcher (Club)": "Yoshiro Sotokoba ( Hiroshima Toyo Carp )",
                    "Score": "2\u20130",
                    "Opponent": "Taiy\u014d Whales",
                    "Ballpark": "Hiroshima Municipal Stadium"
                },
                {
                    "Date": "October 6, 1970",
                    "Pitcher (Club)": "Koichiro Sasaki ( Kintetsu Buffaloes )",
                    "Score": "3\u20130",
                    "Opponent": "Nankai Hawks",
                    "Ballpark": "\u014csaka Stadium"
                },
                {
                    "Date": "August 21, 1971",
                    "Pitcher (Club)": "Yoshimasa Takahashi ( Toei Flyers )",
                    "Score": "4\u20130",
                    "Opponent": "Nishitetsu Lions",
                    "Ballpark": "Korakuen Stadium"
                },
                {
                    "Date": "October 10, 1973",
                    "Pitcher (Club)": "Soroku Yagisawa ( Lotte Orions )",
                    "Score": "1\u20130",
                    "Opponent": "Taiheiyo Club Lions",
                    "Ballpark": "Miyagi Stadium"
                },
                {
                    "Date": "August 31, 1978",
                    "Pitcher (Club)": "Yutaro Imai ( Hankyu Braves )",
                    "Score": "5\u20130",
                    "Opponent": "Lotte Orions",
                    "Ballpark": "Miyagi Stadium"
                },
                {
                    "Date": "May 18, 1994",
                    "Pitcher (Club)": "Hiromi Makihara ( Yomiuri Giants )",
                    "Score": "6\u20130",
                    "Opponent": "Hiroshima Toyo Carp",
                    "Ballpark": "Fukuoka Dome"
                },
                {
                    "Date": "November 1, 2007",
                    "Pitcher (Club)": "Daisuke Yamai and Hitoki Iwase ( Chunichi Dragons )",
                    "Score": "1\u20130\u2020",
                    "Opponent": "Hokkaido Nippon-Ham Fighters",
                    "Ballpark": "Nagoya Dome"
                },
                {
                    "Date": "April 10, 2022",
                    "Pitcher (Club)": "R\u014dki Sasaki ( Chiba Lotte Marines )",
                    "Score": "6\u20130",
                    "Opponent": "Orix Buffaloes",
                    "Ballpark": "Zozo Marine Stadium"
                }
            ]
        ]
    }
]